confload/__init__.py
confload/cli.py
confload/config.py
confload/defaults.py
confload/env.py
confload/schema.py
confload/tools.py
confload-0.3.dist-info/LICENSE
confload-0.3.dist-info/METADATA
confload-0.3.dist-info/WHEEL
confload-0.3.dist-info/top_level.txt
confload-0.3.dist-info/RECORD
