Metadata-Version: 2.1
Name: confload
Version: 0.3
Summary: A tool to handle configuration
Home-page: https://github.com/divad1196/ConfLoad
Author: Gallay David
Author-email: davidtennis96@hotmail.com
License: UNKNOWN
Platform: UNKNOWN
Classifier: Programming Language :: Python :: 3
Classifier: License :: OSI Approved :: GNU Affero General Public License v3
Classifier: Operating System :: OS Independent
